doc_search/__init__.py
doc_search/app.py
doc_search/py.typed
doc_search/web.py
doc_search/workflow/__init__.py
dr_doc_search-1.6.3.dist-info/WHEEL
dr_doc_search-1.6.3.dist-info/METADATA
dr_doc_search-1.6.3.dist-info/entry_points.txt
dr_doc_search-1.6.3.dist-info/RECORD
