Metadata-Version: 2.1
Name: dr-doc-search
Version: 1.6.3
Summary: Search through a document using a chat interface
Home-page: https://namuan.github.io/dr-doc-search
License: MIT
Author: namuan
Author-email: github@deskriders.dev
Requires-Python: >=3.8.1,<4.0
Classifier: Development Status :: 4 - Beta
Classifier: Intended Audience :: Developers
Classifier: License :: OSI Approved :: MIT License
Classifier: Operating System :: OS Independent
Classifier: Programming Language :: Python
Classifier: Programming Language :: Python :: 3
Classifier: Programming Language :: Python :: 3.9
Classifier: Programming Language :: Python :: 3.10
Classifier: Programming Language :: Python :: 3.11
Classifier: Programming Language :: Python :: 3
Classifier: Programming Language :: Python :: 3.10
Classifier: Programming Language :: Python :: 3.8
Classifier: Programming Language :: Python :: 3.9
Classifier: Topic :: Software Development :: Libraries :: Python Modules
Classifier: Typing :: Typed
Requires-Dist: faiss-cpu (>=1.7.3,<2.0.0)
Requires-Dist: langchain (>=0.0.57,<0.0.58)
Requires-Dist: openai (>=0.25.0,<0.26.0)
Requires-Dist: panel (>=0.14.2,<0.15.0)
Requires-Dist: py-executable-checklist (==1.4.0)
Requires-Dist: pypdf (>=3.2.0,<4.0.0)
Requires-Dist: pytest (>=7.2.0,<8.0.0)
Requires-Dist: python-dotenv (>=0.21.0,<0.22.0)
Requires-Dist: rich (>=13.0.0,<14.0.0)
Requires-Dist: sentence-transformers (>=2.2.2,<3.0.0)
Requires-Dist: slug (>=2.0,<3.0)
Requires-Dist: transformers (>=4.26.0,<5.0.0)
Project-URL: Documentation, https://namuan.github.io/dr-doc-search
Project-URL: Repository, https://github.com/namuan/dr-doc-search
